flask_crud_api/api.py
flask_crud_api/filter.py
flask_crud_api/models.py
flask_crud_api/orm.py
flask_crud_api/response.py
flask_crud_api/router.py
flask_crud_api/utils.py
flask_crud_api/view.py
flask_crud_api/static/favicon-16x16.png
flask_crud_api/static/favicon-32x32.png
flask_crud_api/static/index.css
flask_crud_api/static/openapi.json
flask_crud_api/static/swagger-initializer.js
flask_crud_api/templates/index.html
flask_crud_api-0.0.1.dist-info/METADATA
flask_crud_api-0.0.1.dist-info/WHEEL
flask_crud_api-0.0.1.dist-info/top_level.txt
flask_crud_api-0.0.1.dist-info/RECORD
