Metadata-Version: 2.4
Name: flask-crud-api
Version: 0.0.1
Summary: 基于flask快速、优雅实现restful接口
Requires-Python: >=3.9
Requires-Dist: flask>=3.1.0
Requires-Dist: flask-migrate>=4.1.0
Requires-Dist: openpyxl>=3.1.5
Requires-Dist: sqlalchemy>=2.0.40
